{
  "record_format_version": "1.0.0",
  "decision_id": "DEC-MQEU8H6R-NV3JNT",
  "created_at": "2026-06-15T06:34:21.315Z",
  "canonical_markdown_path": ".aof/decisions/DEC-MQEU8H6R-NV3JNT.md",
  "scope": "requirements-approval",
  "stage": "planning",
  "organization": "AI Organization Framework",
  "request": "初回離脱率を下げたい",
  "need": "新規登録導線全体",
  "intent": "登録完了率を 5% 改善する",
  "context": "context: 新規登録導線全体 / 認証基盤は変更しない | prohibited: 認証基盤は変更しない | success: 登録完了率を 5% 改善する",
  "existing_artifacts_reviewed": [],
  "background_or_prior_decisions": "clarification completed in session SESS-MQEU8H6L-LZ78VI",
  "clarifications_or_assumptions": "今回、何を改善対象とし、どの範囲までを扱いますか => 新規登録導線全体 / 改善成功は、どの指標または状態で判断しますか => 登録完了率を 5% 改善する / 今回、変更してはいけない制約や既存要素はありますか => 認証基盤は変更しない",
  "clarification_summary": "runtime は初回の clarification 回答を取り込み、framing に進める状態になった",
  "unresolved_ambiguity": "",
  "options_considered": [
    "Advance to planning with the current frame",
    "Ask another clarification round before planning",
    "Stop and request manual intake review"
  ],
  "selected_option": "Advance to planning with the current frame",
  "decision_summary": "Clarification has produced a usable frame and the session can advance to planning.",
  "governance_model": "council-of-three",
  "decision_makers": [
    "aof-builder-01 (Builder)",
    "aof-visionary-01 (Visionary)"
  ],
  "governance_rule_applied": "majority-with-guardian-veto",
  "veto_used": "No",
  "why_this_option": "The request now has enough framed need, intent, and context to plan against.",
  "why_other_options_were_not_selected": "Additional clarification is not required for the next planning step, and stopping would discard a usable frame.",
  "policy_priorities_applied": "value > quality > safety > speed > cost",
  "policy_tradeoffs_accepted": "planning starts once framing is usable, even though future review may still reopen the work",
  "actions": [
    "carry the framed need, intent, and context into planning",
    "prepare a Builder-led plan packet",
    "keep clarification history available for audit and reopen"
  ],
  "expected_artifact": "planning packet and initial implementation or design plan",
  "expected_outcome": "the session can enter Builder-led planning with a stable framed request",
  "completion_criteria": "framed request is recorded and a planning-stage decision exists",
  "success_criteria": "planning can proceed without reopening clarification immediately",
  "completion_approval_scope": "requirements-approval",
  "success_evaluation_scope": "planning-stage startup review",
  "forecast_required": false,
  "forecast_summary": "not required before initial planning begins",
  "uncertainty_notes": "planning may still reopen clarification if feasibility or risk gaps emerge",
  "actor_performance_notes": "not evaluated yet",
  "capacity_notes": "not evaluated yet",
  "fit_notes": "Builder-led planning is now appropriate because the framing gate is complete",
  "protocol_thread_id": "SESS-MQEU8H6L-LZ78VI",
  "routing_mode": "fast-track",
  "max_retries": 2,
  "escalation_target": "human-maintainer",
  "context_snapshot_id": "CTX-MQEU8H6Q-MTNG32",
  "change_trigger": "clarification answers completed the initial frame",
  "review_trigger": "when planning yields a proposal or reopens clarification",
  "review_date_or_condition": "at planning completion or on new blocking ambiguity",
  "reopen_conditions": "new conflicting signal, weak planning feasibility, or policy conflict",
  "clarification_questions": []
}
